generate_receipt.py
generate_receipt_elf_unic-0.1.0.dist-info/METADATA
generate_receipt_elf_unic-0.1.0.dist-info/WHEEL
generate_receipt_elf_unic-0.1.0.dist-info/entry_points.txt
generate_receipt_elf_unic-0.1.0.dist-info/top_level.txt
generate_receipt_elf_unic-0.1.0.dist-info/RECORD
